{"__symbolic":"module","version":1,"metadata":{"ChatsPage":{"__symbolic":"class","decorators":[{"__symbolic":"call","expression":{"__symbolic":"reference","module":"@angular/core","name":"Component"},"arguments":[{"selector":"page-chats","templateUrl":"chats.html"}]}],"members":{"__ctor__":[{"__symbolic":"constructor","parameters":[{"__symbolic":"reference","module":"ionic-angular","name":"NavController"},{"__symbolic":"reference","module":"../../services/chat-service","name":"ChatService"}]}],"viewChat":[{"__symbolic":"method"}]}}}}